calco/__init__.py
calco-1.1.0.dist-info/licenses/LICENSE
calco-1.1.0.dist-info/METADATA
calco-1.1.0.dist-info/WHEEL
calco-1.1.0.dist-info/top_level.txt
calco-1.1.0.dist-info/RECORD
