Metadata-Version: 2.4
Name: calco
Version: 1.1.0
Summary: High-performance math library for Python (powered by C)
Home-page: https://calcolib.netlify.app
Author: Gafoo
Author-email: gafarssprts@gmail.com
License: MIT
Classifier: Programming Language :: Python :: 3
Classifier: Programming Language :: C
Classifier: Operating System :: OS Independent
Classifier: License :: OSI Approved :: MIT License
Classifier: Topic :: Scientific/Engineering :: Mathematics
Requires-Python: >=3.8
License-File: LICENSE
Dynamic: author
Dynamic: author-email
Dynamic: classifier
Dynamic: description
Dynamic: description-content-type
Dynamic: home-page
Dynamic: license
Dynamic: license-file
Dynamic: requires-python
Dynamic: summary
